fw_dataset/__init__.py
fw_dataset/admin/__init__.py
fw_dataset/admin/admin_helpers.py
fw_dataset/admin/constants.py
fw_dataset/admin/custom_info_table_builder.py
fw_dataset/admin/dataset_builder.py
fw_dataset/admin/default_container_schemas/acquisitions.schema.json
fw_dataset/admin/default_container_schemas/analyses.schema.json
fw_dataset/admin/default_container_schemas/column_control.schema.json
fw_dataset/admin/default_container_schemas/files.schema.json
fw_dataset/admin/default_container_schemas/sessions.schema.json
fw_dataset/admin/default_container_schemas/subjects.schema.json
fw_dataset/admin/exceptions.py
fw_dataset/admin/tabular_file_table_builder.py
fw_dataset/dataset_client.py
fw_dataset/filesystem.py
fw_dataset/fw_dataset.py
fw_dataset/models.py
fw_dataset/templates/dataset_README.md.j2
fw_dataset/templates/version_README.md.j2
fw_dataset/templates/versions_README.md.j2
fw_dataset-0.2.0.dist-info/METADATA
fw_dataset-0.2.0.dist-info/WHEEL
fw_dataset-0.2.0.dist-info/RECORD
