Metadata-Version: 2.3
Name: fw-dataset
Version: 0.2.0
Summary: A library for working with Flywheel datasets
Author: joshicola
Author-email: joshuajacobs@flywheel.io
Requires-Python: >=3.10,<4.0
Classifier: Programming Language :: Python :: 3
Classifier: Programming Language :: Python :: 3.10
Classifier: Programming Language :: Python :: 3.11
Classifier: Programming Language :: Python :: 3.12
Classifier: Programming Language :: Python :: 3.13
Requires-Dist: adlfs (>=2024.7.0,<2025.0.0)
Requires-Dist: deepdiff (>=8.4,<9.0)
Requires-Dist: duckdb (>=1.1.1,<2.0.0)
Requires-Dist: flywheel-sdk (>=20,<21)
Requires-Dist: fsspec (>=2024.9.0,<2025.0.0)
Requires-Dist: fw-client (>=0.8.6,<0.9.0)
Requires-Dist: gcsfs (>=2024.9.0.post1,<2025.0.0)
Requires-Dist: h11 (>=0.16.0,<0.17.0)
Requires-Dist: httpcore (>=1.0.0,<2.0.0)
Requires-Dist: httpx (>=0.28.1,<0.29.0)
Requires-Dist: jinja2 (>=3.1.4,<4.0.0)
Requires-Dist: orjson (>=3.10.7,<4.0.0)
Requires-Dist: pandas (>=2.2.3,<3.0.0)
Requires-Dist: pyarrow (>=20.0,<21.0)
Requires-Dist: pydantic (>=2.9.2,<3.0.0)
Requires-Dist: pyopenssl (>=24.2.1,<25.0.0)
Requires-Dist: s3fs (>=2024.9.0,<2025.0.0)
